{
  "type": "FeatureCollection",
  "features": [
    {
      "type": "Feature",
      "properties": {
        "id": "TC1197",
        "line": 108,
        "name": "101 - Liaison étudiante",
        "status": "done",
        "type": "",
        "link": "https://cyclopolisoise.netlify.app/velo-oise-108"
      },
      "geometry": {
        "coordinates": [
          [
            2.8058040825,
            49.4038507667
          ],
          [
            2.8057848742,
            49.4038601245
          ],
          [
            2.8057738904,
            49.403869348
          ],
          [
            2.8057678239,
            49.4038848287
          ],
          [
            2.8057598379,
            49.4039113341
          ],
          [
            2.8057500998,
            49.4039444439
          ],
          [
            2.8058117211,
            49.4040061467
          ],
          [
            2.8058376557,
            49.404028978
          ],
          [
            2.8058690785,
            49.4040491369
          ],
          [
            2.8059053013,
            49.4040675161
          ],
          [
            2.8059531751,
            49.4040832329
          ],
          [
            2.8060092658,
            49.4040989628
          ],
          [
            2.8060329498,
            49.4041129417
          ],
          [
            2.8060434277,
            49.4041191261
          ],
          [
            2.8062370989,
            49.4043341961
          ],
          [
            2.8076464521,
            49.4059160643
          ],
          [
            2.8077404795,
            49.4060205796
          ],
          [
            2.8077645618,
            49.4060467029
          ],
          [
            2.8078014456,
            49.4060715973
          ]
        ],
        "type": "LineString"
      }
    },
    {
      "type": "Feature",
      "properties": {
        "id": "TC1207",
        "line": 108,
        "name": "101 - Liaison étudiante",
        "status": "done",
        "type": "",
        "link": "https://cyclopolisoise.netlify.app/velo-oise-108"
      },
      "geometry": {
        "coordinates": [
          [
            2.8031919704,
            49.4009264217
          ],
          [
            2.803240252,
            49.4009749015
          ],
          [
            2.8034408404,
            49.4012018671
          ],
          [
            2.8038701212,
            49.4016810187
          ],
          [
            2.8045786324,
            49.4024752766
          ],
          [
            2.8052436772,
            49.403224537
          ],
          [
            2.8054026565,
            49.4034043709
          ],
          [
            2.8058040825,
            49.4038507667
          ]
        ],
        "type": "LineString"
      }
    },
    {
      "type": "Feature",
      "properties": {
        "id": "TC1209",
        "line": 108,
        "name": "101 - Liaison étudiante",
        "status": "done",
        "type": "",
        "link": "https://cyclopolisoise.netlify.app/velo-oise-108"
      },
      "geometry": {
        "type": "LineString",
        "coordinates": [
          [
            2.8031919704,
            49.4009264217
          ],
          [
            2.8031319518,
            49.4009673731
          ],
          [
            2.8029722243,
            49.4010931888
          ],
          [
            2.8028938424,
            49.401177964
          ],
          [
            2.8026362604,
            49.401509558
          ],
          [
            2.8025718832,
            49.4015724611
          ],
          [
            2.8025196871,
            49.4016134867
          ],
          [
            2.8021092951,
            49.4018550128
          ],
          [
            2.8017840287,
            49.4020385856
          ],
          [
            2.8015465977,
            49.4021722535
          ],
          [
            2.8014133674,
            49.4022551395
          ],
          [
            2.8013674938,
            49.4022233256
          ],
          [
            2.8013100582,
            49.402254913
          ],
          [
            2.8013090942,
            49.402255491
          ]
        ]
      }
    },
    {
      "type": "Feature",
      "properties": {
        "id": "TC1210",
        "line": 108,
        "name": "101 - Liaison étudiante",
        "status": "done",
        "type": "bandes-cyclables",
        "link": "https://cyclopolisoise.netlify.app/velo-oise-108"
      },
      "geometry": {
        "type": "LineString",
        "coordinates": [
          [
            2.8013090942,
            49.402255491
          ],
          [
            2.8008999396,
            49.401945681
          ],
          [
            2.8006121138,
            49.4017277373
          ],
          [
            2.7998404999,
            49.401147005
          ],
          [
            2.7989581266,
            49.4004834346
          ]
        ]
      }
    },
    {
      "type": "Feature",
      "properties": {
        "id": "TC1211",
        "line": 108,
        "name": "101 - Liaison étudiante",
        "status": "done",
        "type": "bandes-cyclables",
        "link": "https://cyclopolisoise.netlify.app/velo-oise-108"
      },
      "geometry": {
        "type": "LineString",
        "coordinates": [
          [
            2.8048985619,
            49.4049511479
          ],
          [
            2.8044856453,
            49.4046389497
          ],
          [
            2.8039603214,
            49.404244246
          ],
          [
            2.8034328444,
            49.4038494216
          ],
          [
            2.8033297567,
            49.4037720393
          ],
          [
            2.803082401,
            49.4035863615
          ],
          [
            2.8029771797,
            49.4035073765
          ],
          [
            2.8023291617,
            49.4030172127
          ],
          [
            2.8017363989,
            49.4025751312
          ],
          [
            2.8014072136,
            49.4023295057
          ],
          [
            2.8013090942,
            49.402255491
          ]
        ]
      }
    },
    {
      "type": "Feature",
      "properties": {
        "id": "TC1212",
        "line": 108,
        "name": "101 - Liaison étudiante",
        "status": "done",
        "type": "bandes-cyclables",
        "link": "https://cyclopolisoise.netlify.app/velo-oise-108"
      },
      "geometry": {
        "coordinates": [
          [
            2.8072066989,
            49.4066846282
          ],
          [
            2.8070151636,
            49.4065356474
          ],
          [
            2.8069410583,
            49.4064794229
          ],
          [
            2.8062893079,
            49.4059864385
          ],
          [
            2.8055211148,
            49.4054128948
          ],
          [
            2.8048985619,
            49.4049511479
          ]
        ],
        "type": "LineString"
      }
    },
    {
      "type": "Feature",
      "properties": {
        "id": "TC1213",
        "line": 108,
        "name": "101 - Liaison étudiante",
        "status": "done",
        "type": "",
        "link": "https://cyclopolisoise.netlify.app/velo-oise-108"
      },
      "geometry": {
        "type": "LineString",
        "coordinates": [
          [
            2.8078014456,
            49.4060715973
          ],
          [
            2.8077365719,
            49.4061127453
          ],
          [
            2.8073881309,
            49.4063154997
          ],
          [
            2.8071000171,
            49.4064849556
          ],
          [
            2.8070151636,
            49.4065356474
          ]
        ]
      }
    },
    {
      "type": "Feature",
      "properties": {
        "id": "TC1215",
        "line": 108,
        "name": "101 - Liaison étudiante",
        "status": "done",
        "type": "bandes-cyclables",
        "link": "https://cyclopolisoise.netlify.app/velo-oise-108"
      },
      "geometry": {
        "coordinates": [
          [
            2.8160166393,
            49.4115175354
          ],
          [
            2.8144206275,
            49.4106253972
          ],
          [
            2.8134402555,
            49.4100754294
          ],
          [
            2.8123528879,
            49.4094731557
          ],
          [
            2.8118066882,
            49.4091803959
          ],
          [
            2.8112824652,
            49.4088994098
          ],
          [
            2.8107968572,
            49.4086233868
          ],
          [
            2.8103990629,
            49.4083977814
          ],
          [
            2.81002759,
            49.4081857692
          ],
          [
            2.8096595545,
            49.4079809913
          ],
          [
            2.8091872126,
            49.4077181723
          ]
        ],
        "type": "LineString"
      }
    },
    {
      "type": "Feature",
      "properties": {
        "id": "TC1236",
        "line": 108,
        "name": "101 - Liaison étudiante",
        "status": "done",
        "type": "",
        "link": "https://cyclopolisoise.netlify.app/velo-oise-108"
      },
      "geometry": {
        "coordinates": [
          [
            2.8179370899,
            49.4166847488
          ],
          [
            2.8179606337,
            49.4166649202
          ],
          [
            2.8179823036,
            49.4166598675
          ],
          [
            2.8180108641,
            49.4166655608
          ],
          [
            2.8180471933,
            49.4166786113
          ],
          [
            2.8180705714,
            49.4166803416
          ],
          [
            2.8181000319,
            49.4166764306
          ],
          [
            2.8181076405,
            49.416673344
          ],
          [
            2.8181277862,
            49.4166651715
          ],
          [
            2.8181573085,
            49.4166437445
          ],
          [
            2.8184584099,
            49.4163868635
          ],
          [
            2.8185438842,
            49.4163145477
          ]
        ],
        "type": "LineString"
      }
    },
    {
      "type": "Feature",
      "properties": {
        "id": "TC1238",
        "line": 108,
        "name": "101 - Liaison étudiante",
        "status": "done",
        "type": "bandes-cyclables",
        "link": "https://cyclopolisoise.netlify.app/velo-oise-108"
      },
      "geometry": {
        "coordinates": [
          [
            2.8181050282,
            49.4167722604
          ],
          [
            2.8179370899,
            49.4166847488
          ],
          [
            2.8178208579,
            49.4166252377
          ],
          [
            2.8177657628,
            49.4165974558
          ],
          [
            2.8177144453,
            49.4165682629
          ],
          [
            2.8176521048,
            49.4165291808
          ],
          [
            2.8175877763,
            49.416484487
          ],
          [
            2.8175382598,
            49.4164446055
          ],
          [
            2.8174830357,
            49.416396489
          ],
          [
            2.8174138887,
            49.4163325662
          ],
          [
            2.817323767,
            49.416245123
          ],
          [
            2.8172915311,
            49.4162125003
          ]
        ],
        "type": "LineString"
      }
    },
    {
      "type": "Feature",
      "properties": {
        "id": "TC1239",
        "line": 108,
        "name": "101 - Liaison étudiante",
        "status": "EN PROJET",
        "type": "voie-verte",
        "link": "https://cyclopolisoise.netlify.app/velo-oise-108"
      },
      "geometry": {
        "type": "LineString",
        "coordinates": [
          [
            2.8169654393,
            49.4164418579
          ],
          [
            2.8171132179,
            49.4163380616
          ],
          [
            2.8172915311,
            49.4162125003
          ]
        ]
      }
    },
    {
      "type": "Feature",
      "properties": {
        "type": "perspective",
        "name": "Point Repere",
        "imgUrl": "https://www.velooise.fr/wp-content/uploads/2025/08/cyclopolis-arc-108.jpg",
        "line": 108
      },
      "geometry": {
        "type": "Point",
        "coordinates": [
          2.8169654393,
          49.4164418579
        ]
      }
    }
  ]
}